sage_mailbox/__init__.py
sage_mailbox/admin/__init__.py
sage_mailbox/admin/actions/__init__.py
sage_mailbox/admin/actions/email.py
sage_mailbox/admin/actions/mailbox.py
sage_mailbox/admin/email.py
sage_mailbox/admin/mailbox.py
sage_mailbox/admin/mixins/__init__.py
sage_mailbox/admin/mixins/email.py
sage_mailbox/apps.py
sage_mailbox/checks.py
sage_mailbox/conf.py
sage_mailbox/constants.py
sage_mailbox/exc.py
sage_mailbox/locale/ar/LC_MESSAGES/django.po
sage_mailbox/locale/en/LC_MESSAGES/django.po
sage_mailbox/locale/fa/LC_MESSAGES/django.po
sage_mailbox/migrations/__init__.py
sage_mailbox/models/__init__.py
sage_mailbox/models/attachment.py
sage_mailbox/models/email.py
sage_mailbox/models/flag.py
sage_mailbox/models/mailbox.py
sage_mailbox/models/mixins/__init__.py
sage_mailbox/models/mixins/timestamp.py
sage_mailbox/repository/__init__.py
sage_mailbox/repository/manager.py
sage_mailbox/repository/queryset.py
sage_mailbox/repository/service.py
sage_mailbox/signals/__init__.py
sage_mailbox/signals/email.py
sage_mailbox/templates/admin/email/change_list.html
sage_mailbox/templates/admin/mailbox/change_list.html
sage_mailbox/templatetags/__init__.py
sage_mailbox/templatetags/sage_mailbox.py
sage_mailbox/tests/__init__.py
sage_mailbox/tests/models/__init__.py
sage_mailbox/tests/models/test_email.py
sage_mailbox/tests/repository/__init__.py
sage_mailbox/tests/repository/test_queryset.py
sage_mailbox/tests/repository/test_service.py
sage_mailbox/tests/validators/__init__.py
sage_mailbox/tests/validators/test_comma_separated.py
sage_mailbox/tests/validators/test_folder_name.py
sage_mailbox/utils.py
sage_mailbox/validators.py
django_sage_mailbox-0.2.3.dist-info/LICENSE
django_sage_mailbox-0.2.3.dist-info/METADATA
django_sage_mailbox-0.2.3.dist-info/WHEEL
django_sage_mailbox-0.2.3.dist-info/RECORD
